sqlalchemize/__init__.py
sqlalchemize/create.py
sqlalchemize/delete.py
sqlalchemize/drop.py
sqlalchemize/exceptions.py
sqlalchemize/features.py
sqlalchemize/insert.py
sqlalchemize/records.py
sqlalchemize/select.py
sqlalchemize/test_setup.py
sqlalchemize/type_convert.py
sqlalchemize/types.py
sqlalchemize/update.py
sqlalchemize-0.7.1.dist-info/LICENSE
sqlalchemize-0.7.1.dist-info/METADATA
sqlalchemize-0.7.1.dist-info/WHEEL
sqlalchemize-0.7.1.dist-info/top_level.txt
sqlalchemize-0.7.1.dist-info/RECORD
